slgaas_cli/__init__.py
slgaas_cli/cliutils.py
slgaas_cli-1.0.61.data/data/bin/config-gw.py
slgaas_cli-1.0.61.data/data/bin/manage-gw.py
slgaas_cli-1.0.61.data/data/bin/order-gw.py
slgaas_cli-1.0.61.dist-info/DESCRIPTION.rst
slgaas_cli-1.0.61.dist-info/METADATA
slgaas_cli-1.0.61.dist-info/RECORD
slgaas_cli-1.0.61.dist-info/WHEEL
slgaas_cli-1.0.61.dist-info/metadata.json
slgaas_cli-1.0.61.dist-info/pbr.json
slgaas_cli-1.0.61.dist-info/top_level.txt
