Metadata-Version: 2.0
Name: slgaas-cli
Version: 1.0.61
Summary: CLI for SoftLayer Gateway as a Service
Home-page: https://gateway-as-a-service.com/
Author: Khoa Huynh
Author-email: bp@us.ibm.com
License: Eclipse
Keywords: setup
Requires-Dist: requests (==2.6.2)
Requires-Dist: simplejson (==3.6.5)
